.gitignore
.travis.yml
LICENSE
MANIFEST.in
README.md
setup.cfg
setup.py
tox.ini
django_mail_templated_simple.egg-info/PKG-INFO
django_mail_templated_simple.egg-info/SOURCES.txt
django_mail_templated_simple.egg-info/dependency_links.txt
django_mail_templated_simple.egg-info/not-zip-safe
django_mail_templated_simple.egg-info/top_level.txt
mail_templated_simple/__init__.py
mail_templated_simple/models.py
mail_templated_simple/templates/mail_templated_simple/base.tpl
mail_templated_simple_tests/__init__.py
mail_templated_simple_tests/models.py
mail_templated_simple_tests/tests.py
mail_templated_simple_tests/templates/mail_templated_simple_tests/full_example.tpl
mail_templated_simple_tests/templates/mail_templated_simple_tests/html_only_example.tpl
mail_templated_simple_tests/templates/mail_templated_simple_tests/plaintext_only_example.tpl
unittest_project/manage.py
unittest_project/unittest_project/__init__.py
unittest_project/unittest_project/settings.py
unittest_project/unittest_project/urls.py