Metadata-Version: 1.1
Name: django-mail-templated-simple
Version: 3.2
Summary: A simple reimplementation of "django-mail-templated"
Home-page: https://github.com/jonashaag/django-mail-templated-simple
Author: Jonas Haag
Author-email: jonas@lophus.org
License: ISC
Platform: UNKNOWN
Classifier: Development Status :: 5 - Production/Stable
Classifier: License :: OSI Approved :: ISC License (ISCL)
Classifier: Framework :: Django
Classifier: Programming Language :: Python
Classifier: Programming Language :: Python :: 2
Classifier: Programming Language :: Python :: 2.7
Classifier: Programming Language :: Python :: 3
Classifier: Programming Language :: Python :: 3.4
Classifier: Programming Language :: Python :: 3.5
Classifier: Programming Language :: Python :: 3.6
